randetect/__init__.py
randetect/random_detect.py
randetect/models/logistic_regression_model.joblib
tests/__init__.py
tests/test_preprocess_text.py
tests/test_random_detect.py
randetect-0.0.1.dist-info/METADATA
randetect-0.0.1.dist-info/WHEEL
randetect-0.0.1.dist-info/top_level.txt
randetect-0.0.1.dist-info/RECORD
