Metadata-Version: 2.1
Name: randetect
Version: 0.0.1
Summary: A text analysis tool that predicts whether a given string appears random or meaningful.
Home-page: https://github.com/seymasa/randetect
Author: Seyma SARIGİL
Author-email: seymasa@icloud.com
Classifier: Programming Language :: Python :: 3
Classifier: License :: OSI Approved :: MIT License
Classifier: Operating System :: OS Independent
Requires-Dist: click ==8.1.7
Requires-Dist: emoji ==2.8.0
Requires-Dist: joblib ==1.3.2
Requires-Dist: mintlemon-turkish-nlp ==0.2.5
Requires-Dist: nltk ==3.8.1
Requires-Dist: numpy ==1.25.2
Requires-Dist: pandas ==2.0.0
Requires-Dist: python-dateutil ==2.8.2
Requires-Dist: pytz ==2023.3.post1
Requires-Dist: regex ==2023.8.8
Requires-Dist: scikit-learn ==1.3.0
Requires-Dist: scipy ==1.11.2
Requires-Dist: six ==1.16.0
Requires-Dist: threadpoolctl ==3.2.0
Requires-Dist: tqdm ==4.66.1
Requires-Dist: tzdata ==2023.3
Requires-Dist: zeyrek ==0.1.3
